itk_skullstripping-1.0.1.dist-info/RECORD
itk_skullstripping-1.0.1.dist-info/WHEEL
itk_skullstripping-1.0.1.dist-info/METADATA
itk_skullstripping-1.0.1.dist-info/licenses/LICENSE
itk_skullstripping.libs/libtbb-e046f41a.so.12.9
itk/itkStripTsImageFilterPython.py
itk/_SkullStripPython.cpython-310-aarch64-linux-gnu.so
itk/SkullStripPython.py
itk/Configuration/SkullStrip_snake_case.py
itk/Configuration/SkullStripConfig.py
